setup.py
temporalis/__init__.py
temporalis/exceptions.py
temporalis/location.py
temporalis/moon.py
temporalis/sun.py
temporalis/time.py
temporalis/xml.py
temporalis.egg-info/PKG-INFO
temporalis.egg-info/SOURCES.txt
temporalis.egg-info/dependency_links.txt
temporalis.egg-info/requires.txt
temporalis.egg-info/top_level.txt
temporalis/providers/__init__.py
temporalis/providers/darksky.py
temporalis/providers/owm.py