Metadata-Version: 1.0
Name: temporalis
Version: 0.1
Summary: unified weather service apis
Home-page: https://github.com/HelloChatterbox/pyweather
Author: jarbasAi
Author-email: jarbasai@mailfence.com
License: Apache2
Platform: UNKNOWN
